VkInline/Context.py
VkInline/ContextEX.py
VkInline/Cubemap.py
VkInline/Native.py
VkInline/NativeEX.py
VkInline/PyVkInline.dll
VkInline/PyVkInlineEX.dll
VkInline/SVBuffer.py
VkInline/SVCombine.py
VkInline/SVObjBuffer.py
VkInline/SVObjVector.py
VkInline/SVVector.py
VkInline/ShaderViewable.py
VkInline/Texture2D.py
VkInline/Texture3D.py
VkInline/__init__.py
VkInline/cffi.py
VkInline/libPyVkInline.so
VkInline/libPyVkInlineEX.so
VkInline/utils.py
VkInline-0.3.7.dist-info/METADATA
VkInline-0.3.7.dist-info/WHEEL
VkInline-0.3.7.dist-info/top_level.txt
VkInline-0.3.7.dist-info/RECORD
